<annotation>
	<folder>images</folder>
	<filename>11.jpg</filename>
	<path>/home/robint01/yolov5/data/data_weed&amp;corn/images/11.jpg</path>
	<source>
		<database>Unknown</database>
	</source>
	<size>
		<width>800</width>
		<height>600</height>
		<depth>3</depth>
	</size>
	<segmented>0</segmented>
	<object>
		<name>corn</name>
		<pose>Unspecified</pose>
		<truncated>0</truncated>
		<difficult>0</difficult>
		<bndbox>
			<xmin>379</xmin>
			<ymin>259</ymin>
			<xmax>421</xmax>
			<ymax>341</ymax>
		</bndbox>
	</object>
	<object>
		<name>corn</name>
		<pose>Unspecified</pose>
		<truncated>0</truncated>
		<difficult>0</difficult>
		<bndbox>
			<xmin>58</xmin>
			<ymin>145</ymin>
			<xmax>99</xmax>
			<ymax>196</ymax>
		</bndbox>
	</object>
	<object>
		<name>corn</name>
		<pose>Unspecified</pose>
		<truncated>1</truncated>
		<difficult>0</difficult>
		<bndbox>
			<xmin>373</xmin>
			<ymin>1</ymin>
			<xmax>418</xmax>
			<ymax>52</ymax>
		</bndbox>
	</object>
	<object>
		<name>corn</name>
		<pose>Unspecified</pose>
		<truncated>1</truncated>
		<difficult>0</difficult>
		<bndbox>
			<xmin>270</xmin>
			<ymin>569</ymin>
			<xmax>340</xmax>
			<ymax>600</ymax>
		</bndbox>
	</object>
</annotation>
